cellidentifierdx/__init__.py
cellidentifierdx/cli.py
cellidentifierdx/scoring.py
cellidentifierdx/utils.py
tests/__init__.py
tests/test_scoring.py
cellidentifierdx-0.1.dist-info/LICENSE
cellidentifierdx-0.1.dist-info/METADATA
cellidentifierdx-0.1.dist-info/WHEEL
cellidentifierdx-0.1.dist-info/top_level.txt
cellidentifierdx-0.1.dist-info/RECORD
