Metadata-Version: 2.1
Name: cellidentifierdx
Version: 0.1
Summary: A package to identify cell types using Bayesian scoring
Home-page: https://github.com/yourusername/cellidentifierdx
Author: mdbabumia
Author-email: md.babu.mia@mssm.edu
Classifier: Development Status :: 3 - Alpha
Classifier: License :: OSI Approved :: MIT License
Classifier: Programming Language :: Python :: 3.6
Classifier: Programming Language :: Python :: 3.7
Classifier: Programming Language :: Python :: 3.8
Classifier: Programming Language :: Python :: 3.10
Requires-Python: >=3.6
License-File: LICENSE
